dbt/adapters/fabric/__init__.py
dbt/adapters/fabric/__version__.py
dbt/adapters/fabric/fabric_adapter.py
dbt/adapters/fabric/fabric_api_client.py
dbt/adapters/fabric/fabric_column.py
dbt/adapters/fabric/fabric_configs.py
dbt/adapters/fabric/fabric_connection_manager.py
dbt/adapters/fabric/fabric_credentials.py
dbt/adapters/fabric/fabric_livy_helper.py
dbt/adapters/fabric/fabric_relation.py
dbt/adapters/fabric/fabric_token_provider.py
dbt/adapters/fabric/relation_configs/__init__.py
dbt/adapters/fabric/relation_configs/base.py
dbt/adapters/fabric/relation_configs/policies.py
dbt/include/fabric/__init__.py
dbt/include/fabric/dbt_project.yml
dbt/include/fabric/macros/adapters/apply_grants.sql
dbt/include/fabric/macros/adapters/catalog.sql
dbt/include/fabric/macros/adapters/columns.sql
dbt/include/fabric/macros/adapters/indexes.sql
dbt/include/fabric/macros/adapters/metadata.sql
dbt/include/fabric/macros/adapters/persist_docs.sql
dbt/include/fabric/macros/adapters/relation.sql
dbt/include/fabric/macros/adapters/schema.sql
dbt/include/fabric/macros/adapters/show.sql
dbt/include/fabric/macros/dbt_package_support/dbt_audit_helper/compare_column_values.sql
dbt/include/fabric/macros/dbt_package_support/dbt_audit_helper/compare_queries.sql
dbt/include/fabric/macros/dbt_package_support/dbt_audit_helper/compare_relation_columns.sql
dbt/include/fabric/macros/dbt_package_support/dbt_audit_helper/compare_relations.sql
dbt/include/fabric/macros/dbt_package_support/dbt_date/get_date_dimension.sql
dbt/include/fabric/macros/dbt_package_support/dbt_date/_utils/day_name.sql
dbt/include/fabric/macros/dbt_package_support/dbt_date/_utils/month_name.sql
dbt/include/fabric/macros/dbt_package_support/dbt_date/calendar_date/convert_timezones.sql
dbt/include/fabric/macros/dbt_package_support/dbt_date/calendar_date/date_part.sql
dbt/include/fabric/macros/dbt_package_support/dbt_date/calendar_date/day_of_week.sql
dbt_fabric_samdebruyn-1.10.1.dist-info/METADATA
dbt_fabric_samdebruyn-1.10.1.dist-info/WHEEL
dbt_fabric_samdebruyn-1.10.1.dist-info/licenses/LICENSE
dbt_fabric_samdebruyn-1.10.1.dist-info/RECORD
