Metadata-Version: 2.4
Name: dbt-fabric-samdebruyn
Version: 1.10.1
Summary: A Microsoft Fabric Synapse Data Warehouse adapter plugin for dbt
Project-URL: Documentation, http://dbt-fabric.debruyn.dev/
Project-URL: Changelog, https://github.com/sdebruyn/dbt-fabric/releases
Project-URL: Issue Tracker, https://github.com/sdebruyn/dbt-fabric/issues
Project-URL: Homepage, https://github.com/sdebruyn/dbt-fabric
Author: Sam Debruyn
License-Expression: MIT
License-File: LICENSE
Classifier: Development Status :: 5 - Production/Stable
Classifier: Operating System :: MacOS :: MacOS X
Classifier: Operating System :: Microsoft :: Windows
Classifier: Operating System :: POSIX :: Linux
Classifier: Programming Language :: Python :: 3.10
Classifier: Programming Language :: Python :: 3.11
Classifier: Programming Language :: Python :: 3.12
Classifier: Programming Language :: Python :: 3.13
Requires-Python: <3.14,>=3.10
Requires-Dist: azure-identity>=1.12.0
Requires-Dist: dbt-adapters<2.0,>=1.1.1
Requires-Dist: dbt-common<2.0,>=1.0.4
Requires-Dist: pyodbc>=4.0.35
Requires-Dist: requests>=2.32.3
